socian_auth/__init__.py
socian_auth/api_client.py
Socian_Auth_SDK-0.1.0.dist-info/LICENSE
Socian_Auth_SDK-0.1.0.dist-info/METADATA
Socian_Auth_SDK-0.1.0.dist-info/WHEEL
Socian_Auth_SDK-0.1.0.dist-info/top_level.txt
Socian_Auth_SDK-0.1.0.dist-info/RECORD
